dictparse/__init__.py
dictparse/exceptions.py
dictparse/parser.py
tests/__init__.py
tests/test_namespace.py
tests/test_parser.py
dictparse-1.4.dist-info/LICENSE
dictparse-1.4.dist-info/METADATA
dictparse-1.4.dist-info/WHEEL
dictparse-1.4.dist-info/top_level.txt
dictparse-1.4.dist-info/RECORD
