Metadata-Version: 2.1
Name: dictparse
Version: 1.4
Summary: A Python dictionary parser
Home-page: https://github.com/Julian-Nash/dictparse
Author: Julian Nash
Author-email: julianjamesnash@gmail.com
License: UNKNOWN
Project-URL: Bug Tracker, https://github.com/Julian-Nash/dictparse
Project-URL: Documentation, https://github.com/Julian-Nash/dictparse
Project-URL: Source Code, https://github.com/Julian-Nash/dictparse
Keywords: dict dictionary parser flask django validation request json
Platform: UNKNOWN
Classifier: Intended Audience :: Developers
Classifier: License :: OSI Approved :: MIT License
Classifier: Programming Language :: Python :: 3.6
Classifier: Programming Language :: Python :: 3.7
Classifier: Programming Language :: Python :: 3.8
